h_music/__init__.py
h_music/__main__.py
h_music/Empty/AlbumEmpty.py
h_music/Empty/BaseAlbumEmpty.py
h_music/Empty/BaseEmpty.py
h_music/Empty/LyricEmpty.py
h_music/Empty/MusicInfoEmpty.py
h_music/Empty/ResultEmpty.py
h_music/Empty/SearchEmpty.py
h_music/Empty/SingerEmpty.py
h_music/Empty/SongEmpty.py
h_music/Empty/__init__.py
h_music/Site/KuGou.py
h_music/Site/KuWo.py
h_music/Site/MiGu.py
h_music/Site/NetEase.py
h_music/Site/QQ.py
h_music/Site/QianQian.py
h_music/Site/__init__.py
h_music/Utils/__init__.py
h_music/Utils/prettytable.py
h_music/Utils/request.py
h_music/Utils/transform.py
h_music-0.1.4.dist-info/LICENSE
h_music-0.1.4.dist-info/METADATA
h_music-0.1.4.dist-info/WHEEL
h_music-0.1.4.dist-info/entry_points.txt
h_music-0.1.4.dist-info/top_level.txt
h_music-0.1.4.dist-info/RECORD
